optics_framework/.DS_Store
optics_framework/.claude/settings.local.json
optics_framework/__init__.py
optics_framework/api/.DS_Store
optics_framework/api/__init__.py
optics_framework/api/action_keyword.py
optics_framework/api/app_management.py
optics_framework/api/flow_control.py
optics_framework/api/verifier.py
optics_framework/common/Junit_eventhandler.py
optics_framework/common/__init__.py
optics_framework/common/async_utils.py
optics_framework/common/base_factory.py
optics_framework/common/config_handler.py
optics_framework/common/driver_interface.py
optics_framework/common/elementsource_interface.py
optics_framework/common/error.py
optics_framework/common/eventSDK.py
optics_framework/common/events.py
optics_framework/common/execution.py
optics_framework/common/execution_tracer.py
optics_framework/common/expose_api.py
optics_framework/common/factories.py
optics_framework/common/image_interface.py
optics_framework/common/logging_config.py
optics_framework/common/models.py
optics_framework/common/optics_builder.py
optics_framework/common/runner/__init__.py
optics_framework/common/runner/data_reader.py
optics_framework/common/runner/keyword_register.py
optics_framework/common/runner/printers.py
optics_framework/common/runner/test_runnner.py
optics_framework/common/screenshot_stream.py
optics_framework/common/session_manager.py
optics_framework/common/strategies.py
optics_framework/common/test_context.py
optics_framework/common/text_interface.py
optics_framework/common/utils.py
optics_framework/config_usage.md
optics_framework/engines/__init__.py
optics_framework/engines/drivers/__init__.py
optics_framework/engines/drivers/appium.py
optics_framework/engines/drivers/appium_UI_helper.py
optics_framework/engines/drivers/ble.py
optics_framework/engines/drivers/playwright.py
optics_framework/engines/drivers/selenium.py
optics_framework/engines/drivers/selenium_UI_helper.py
optics_framework/engines/elementsources/__init__.py
optics_framework-1.8.0.dist-info/LICENSE
optics_framework-1.8.0.dist-info/METADATA
optics_framework-1.8.0.dist-info/WHEEL
optics_framework-1.8.0.dist-info/entry_points.txt
optics_framework-1.8.0.dist-info/RECORD
