Metadata-Version: 2.3
Name: optics-framework
Version: 1.8.0
Summary: A flexible and modular test automation framework that can be used to automate any mobile application.
License: Apache-2.0
Keywords: test automation,framework,mobile automation
Author: Lalitanand Dandge
Author-email: lalit@mozark.ai
Requires-Python: >=3.12,<4.0
Classifier: Intended Audience :: Developers
Classifier: License :: OSI Approved :: Apache Software License
Classifier: Operating System :: OS Independent
Classifier: Programming Language :: Python :: 3
Classifier: Programming Language :: Python :: 3.12
Classifier: Programming Language :: Python :: 3.13
Classifier: Topic :: Software Development :: Testing
Requires-Dist: fastapi (>=0.115.12,<0.119.0)
Requires-Dist: fuzzywuzzy (>=0.18.0,<0.19.0)
Requires-Dist: jsonpath-ng (>=1.7.0,<2.0.0)
Requires-Dist: lxml (>=5.3.1,<7.0.0)
Requires-Dist: opencv-python (>=4.11.0.86,<5.0.0.0)
Requires-Dist: pandas (>=2.2.3,<3.0.0)
Requires-Dist: prompt-toolkit (>=3.0.50,<4.0.0)
Requires-Dist: pydantic (>=2.11.2,<3.0.0)
Requires-Dist: pytest (>=8.3.5,<9.0.0)
Requires-Dist: python-json-logger (>=3.3,<5.0)
Requires-Dist: python-levenshtein (>=0.27.1,<0.28.0)
Requires-Dist: pyyaml (>=6.0.2,<7.0.0)
Requires-Dist: requests (>=2.32.3,<3.0.0)
Requires-Dist: rich (>=13.9.4,<15.0.0)
Requires-Dist: scikit-image (>=0.25.2,<0.26.0)
Requires-Dist: sse-starlette (>=2.2.1,<4.0.0)
Requires-Dist: textual (>=3,<7)
Requires-Dist: typing_extensions (>=4.13.0)
Requires-Dist: uvicorn (>=0.35,<0.38)
Project-URL: Documentation, https://mozarkai.github.io/optics-framework/
Project-URL: Homepage, https://github.com/mozarkai/optics-framework
Project-URL: Repository, https://github.com/mozarkai/optics-framework
